LICENSE
README.md
setup.py
Pycord_Utils.egg-info/PKG-INFO
Pycord_Utils.egg-info/SOURCES.txt
Pycord_Utils.egg-info/dependency_links.txt
Pycord_Utils.egg-info/requires.txt
Pycord_Utils.egg-info/top_level.txt
pycord/ext/alternatives/__init__.py
pycord/ext/alternatives/_common.py
pycord/ext/alternatives/asset_converter.py
pycord/ext/alternatives/binary_checks.py
pycord/ext/alternatives/bot_send_help.py
pycord/ext/alternatives/category_channel.py
pycord/ext/alternatives/class_command.py
pycord/ext/alternatives/command_piping.py
pycord/ext/alternatives/command_suffix.py
pycord/ext/alternatives/converter_dict.py
pycord/ext/alternatives/dict_converter.py
pycord/ext/alternatives/fix_4098.py
pycord/ext/alternatives/guild_converter.py
pycord/ext/alternatives/inline_bot_commands.py
pycord/ext/alternatives/int_map.py
pycord/ext/alternatives/jump_url.py
pycord/ext/alternatives/literal_converter.py
pycord/ext/alternatives/material_colors.py
pycord/ext/alternatives/material_colours.py
pycord/ext/alternatives/message_eq.py
pycord/ext/alternatives/messageable_wait_for.py
pycord/ext/alternatives/object_contains.py
pycord/ext/alternatives/role.py
pycord/ext/alternatives/silent_delete.py
pycord/ext/alternatives/specific_error_handler.py
pycord/ext/alternatives/subcommand_error.py
pycord/ext/alternatives/webhook_channel.py
pycord/ext/audio/__init__.py
pycord/ext/audio/backoff.py
pycord/ext/audio/client.py
pycord/ext/audio/eqs.py
pycord/ext/audio/errors.py
pycord/ext/audio/events.py
pycord/ext/audio/meta.py
pycord/ext/audio/node.py
pycord/ext/audio/player.py
pycord/ext/audio/stats.py
pycord/ext/audio/websocket.py
pycord/ext/dl/YoutubeDL.py
pycord/ext/dl/__init__.py
pycord/ext/dl/__main__.py
pycord/ext/dl/aes.py
pycord/ext/dl/cache.py
pycord/ext/dl/compat.py
pycord/ext/dl/jsinterp.py
pycord/ext/dl/options.py
pycord/ext/dl/socks.py
pycord/ext/dl/swfinterp.py
pycord/ext/dl/update.py
pycord/ext/dl/utils.py
pycord/ext/dl/version.py
pycord/ext/dl/downloader/__init__.py
pycord/ext/dl/downloader/common.py
pycord/ext/dl/downloader/dash.py
pycord/ext/dl/downloader/external.py
pycord/ext/dl/downloader/f4m.py
pycord/ext/dl/downloader/fragment.py
