Metadata-Version: 2.1
Name: Pycord-Utils
Version: 2.3.2
Summary: Utility Plugin For Pycord
Home-page: https://github.com/pycord/utilitys
Author: pycord
License: MIT
Platform: UNKNOWN
Classifier: License :: OSI Approved :: MIT License
Classifier: Intended Audience :: Developers
Classifier: Natural Language :: English
Classifier: Operating System :: OS Independent
Classifier: Programming Language :: Python :: 3.8
Classifier: Programming Language :: Python :: 3.9
Classifier: Programming Language :: Python :: 3.10
Classifier: Topic :: Internet
Classifier: Topic :: Software Development :: Libraries
Classifier: Topic :: Software Development :: Libraries :: Python Modules
Classifier: Topic :: Utilities
Classifier: Typing :: Typed
Requires-Python: >=3.8
Provides-Extra: voice
Provides-Extra: extra
Provides-Extra: docs
Provides-Extra: speed
License-File: LICENSE
